subprocess_execution/__init__.py
subprocess_execution/subprocess_execution.py
subprocess_execution-0.1.1.dist-info/LICENSE
subprocess_execution-0.1.1.dist-info/METADATA
subprocess_execution-0.1.1.dist-info/WHEEL
subprocess_execution-0.1.1.dist-info/top_level.txt
subprocess_execution-0.1.1.dist-info/RECORD
