Metadata-Version: 2.1
Name: subprocess_execution
Version: 0.1.1
Summary: Efficient library for running Python code in isolated subprocesses.
Home-page: https://github.com/joshwadd/subprocess_execution/
Author: josh waddington
Author-email: josh.waddington1@gmail.com
Classifier: Programming Language :: Python :: 3
Requires-Python: >=3.8
License-File: LICENSE
Requires-Dist: cloudpickle>=3.0.0
